weatherlib/__init__.py
weatherlib/historical_weather.py
weather_lib-0.1.0.dist-info/METADATA
weather_lib-0.1.0.dist-info/WHEEL
weather_lib-0.1.0.dist-info/top_level.txt
weather_lib-0.1.0.dist-info/RECORD
